djff2html/__init__.py
djff2html/j.py
djff2html/v.py
djff2html-0.1.0.dist-info/LICENSE
djff2html-0.1.0.dist-info/METADATA
djff2html-0.1.0.dist-info/WHEEL
djff2html-0.1.0.dist-info/top_level.txt
djff2html-0.1.0.dist-info/RECORD
